.travis.yml
LICENSE.txt
README.md
requirements.txt
setup.py
hyclb/__init__.py
hyclb/cl4hy-deep2-bak.hy
hyclb/cl4hy.hy
hyclb/core.hy
hyclb/models.py
hyclb/util.hy
hyclb.egg-info/PKG-INFO
hyclb.egg-info/SOURCES.txt
hyclb.egg-info/dependency_links.txt
hyclb.egg-info/requires.txt
hyclb.egg-info/top_level.txt
tests/__init__.py
tests/simple.lisp
tests/test_cl4hy.hy
tests/test_cl4hy_load.hy
tests/test_clmacro.hy
tests/test_core.hy
tests/test_hylang.hy
tests/test_internal.hy
tests/test_readme.hy