Metadata-Version: 1.1
Name: hyclb
Version: 0.2.3.3
Summary: hyclb : common-lisp interface and common-lisp-like functions for hylang
Home-page: https://github.com/niitsuma/hycl/
Author: Hirotaka Niitsuma, Riku Togashi
Author-email: hirotaka.niitsuma@gmail.com
License: MIT License
Keywords: hy lisp common-lisp
Platform: any
Classifier: License :: OSI Approved :: MIT License
Classifier: Operating System :: OS Independent
Classifier: Programming Language :: Python :: 3.6
